open5gsapi/__init__.py
open5gsapi/core.py
open5gsapi/exceptions.py
open5gsapi/metrics.py
open5gsapi/sensor_metrics.py
open5gsapi-0.15.1.dist-info/METADATA
open5gsapi-0.15.1.dist-info/WHEEL
open5gsapi-0.15.1.dist-info/top_level.txt
open5gsapi-0.15.1.dist-info/RECORD
