Metadata-Version: 2.1
Name: open5gsapi
Version: 0.15.1
Summary: A Python API for interacting with Open5GS components
Home-page: https://github.com/ashwinsathish/open5gsapi
Author: Ashwin
Author-email: f20200893@pilani.bits-pilani.ac.in
License: UNKNOWN
Platform: UNKNOWN
Classifier: Development Status :: 3 - Alpha
Classifier: Intended Audience :: Developers
Classifier: License :: OSI Approved :: MIT License
Classifier: Operating System :: OS Independent
Classifier: Programming Language :: Python :: 3.9
Requires-Python: >=3.6
Requires-Dist: pyyaml
Requires-Dist: requests
